{
  "place_id": "dcc:place:cn-30-foshan:0001",
  "place_slug": "foshan",
  "place_name": "Foshan",
  "center": {
    "coordinates": [
      113.13148,
      23.02677
    ],
    "country_code": "CN",
    "admin1_code": "30"
  },
  "lane_counts": {
    "tours": 0,
    "cruises": 0,
    "transport": 0,
    "events": 0
  },
  "providers": [],
  "observations": {
    "latest_event_type": null,
    "latest_event_severity": null,
    "trend": "normal"
  },
  "reference_points": [
    {
      "id": "dcc:place:cn-30-guangzhou:0001",
      "slug": "guangzhou",
      "name": "Guangzhou",
      "reason": "near_place_geo",
      "class": "place",
      "coordinates": [
        113.25,
        23.11667
      ]
    },
    {
      "id": "dcc:place:cn-30-jiangmen:0001",
      "slug": "jiangmen",
      "name": "Jiangmen",
      "reason": "near_place_geo",
      "class": "place",
      "coordinates": [
        113.08333,
        22.58333
      ]
    },
    {
      "id": "dcc:place:cn-30-zhongshan:0001",
      "slug": "zhongshan",
      "name": "Zhongshan",
      "reason": "near_place_geo",
      "class": "place",
      "coordinates": [
        113.37912,
        22.52306
      ]
    }
  ],
  "generated_at": "2026-03-09T04:43:00.725Z"
}
