{
  "place_id": "dcc:place:cn-04-xuzhou:0001",
  "place_slug": "xuzhou",
  "place_name": "Xuzhou",
  "center": {
    "coordinates": [
      117.28386,
      34.20442
    ],
    "country_code": "CN",
    "admin1_code": "04"
  },
  "lane_counts": {
    "tours": 0,
    "cruises": 0,
    "transport": 0,
    "events": 0
  },
  "providers": [],
  "observations": {
    "latest_event_type": null,
    "latest_event_severity": null,
    "trend": "improving"
  },
  "reference_points": [
    {
      "id": "dcc:place:cn-01-huaibei:0001",
      "slug": "huaibei",
      "name": "Huaibei",
      "reason": "near_place_geo",
      "class": "place",
      "coordinates": [
        116.79167,
        33.97444
      ]
    },
    {
      "id": "dcc:place:cn-01-suzhou-2:0001",
      "slug": "suzhou-2",
      "name": "Suzhou",
      "reason": "near_place_geo",
      "class": "place",
      "coordinates": [
        116.97889,
        33.63611
      ]
    },
    {
      "id": "dcc:place:cn-04-suqian:0001",
      "slug": "suqian",
      "name": "Suqian",
      "reason": "near_place_geo",
      "class": "place",
      "coordinates": [
        118.29583,
        33.94917
      ]
    }
  ],
  "generated_at": "2026-03-09T04:43:00.766Z"
}
