{
  "place_id": "dcc:place:mz-04-matola:0001",
  "place_slug": "matola",
  "place_name": "Matola",
  "actions": {
    "tours": [],
    "cruises": [],
    "transport": [],
    "events": []
  },
  "providers": [],
  "observations": {
    "latest_event_type": null,
    "latest_event_severity": null,
    "trend": "normal"
  },
  "related_places": [
    {
      "place_id": "dcc:place:mz-11-maputo:0001",
      "place_slug": "maputo",
      "place_name": "Maputo",
      "reason": "near_place_geo",
      "distance_km": 12.4
    }
  ],
  "counts": {
    "tours": 0,
    "cruises": 0,
    "transport": 0,
    "events": 0
  },
  "edges": [
    {
      "type": "related_to",
      "from": "dcc:place:mz-04-matola:0001",
      "to": "dcc:place:mz-11-maputo:0001",
      "meta": {
        "reason": "near_place_geo"
      }
    }
  ]
}